accuweather_client/__init__.py
accuweather_client/clients/__init__.py
accuweather_client/clients/location.py
accuweather_client/clients/weather.py
accuweather_client/models/__init__.py
accuweather_client/models/_base.py
accuweather_client/models/location.py
accuweather_client/models/weather.py
accuweather_client-1.0.0.dist-info/LICENSE
accuweather_client-1.0.0.dist-info/METADATA
accuweather_client-1.0.0.dist-info/WHEEL
accuweather_client-1.0.0.dist-info/top_level.txt
accuweather_client-1.0.0.dist-info/RECORD
