Metadata-Version: 2.1
Name: accuweather_client
Version: 1.0.0
Summary: The goal of this project is to create a user-friendly api client for AccuWeather api.
Author-email: Thomas <thomas.development1942@gmail.com>
License: MIT
Project-URL: repository, https://github.com/Thomas1942/AccuWeather
Keywords: AccuWeather,API,weather,client,python,pydantic
Requires-Python: >=3.10
License-File: LICENSE
Requires-Dist: pandas==2.2.2
Requires-Dist: pydantic==2.8.2
Requires-Dist: python-dotenv==1.0.1
Requires-Dist: Requests==2.32.3
Requires-Dist: numpy==2.1.0
